wood_rui/__init__.py
wood_rui/command.py
wood_rui/element.py
wood_rui/forms.py
wood_rui/globals.py
wood_rui/groups.py
wood_rui/layer.py
wood_rui/object.py
wood_rui-0.2.2.dist-info/LICENSE.txt
wood_rui-0.2.2.dist-info/METADATA
wood_rui-0.2.2.dist-info/WHEEL
wood_rui-0.2.2.dist-info/top_level.txt
wood_rui-0.2.2.dist-info/RECORD
