Metadata-Version: 2.1
Name: wood_rui
Version: 0.2.2
Summary: A package for managing wood joinery geometries in Rhino8.
Home-page: https://github.com/yourusername/wood_rui
Author: Petras Vestartas
Author-email: your.email@example.com
Classifier: Programming Language :: Python :: 3
Classifier: License :: OSI Approved :: MIT License
Classifier: Operating System :: OS Independent
Requires-Python: >=3.9.10
License-File: LICENSE.txt
